classtree/__init__.py
classtree/__main__.py
classtree/cli.py
classtree/dataset.py
classtree/download.py
classtree/export.py
classtree/hier.py
classtree/loss.py
classtree/metrics.py
classtree/models.py
classtree/predict.py
classtree/test.py
classtree/train.py
classtree-0.0.3.dist-info/LICENSE.txt
classtree-0.0.3.dist-info/METADATA
classtree-0.0.3.dist-info/WHEEL
classtree-0.0.3.dist-info/entry_points.txt
classtree-0.0.3.dist-info/top_level.txt
classtree-0.0.3.dist-info/RECORD
