Metadata-Version: 2.1
Name: classtree
Version: 0.0.3
Summary: A toolkit for hierarchical classification
License: CLASSTREE
Keywords: classification,hierarchical
Classifier: Programming Language :: Python :: 3
Classifier: Operating System :: OS Independent
Requires-Python: <3.12,>=3.9
License-File: LICENSE.txt
Requires-Dist: numpy==1.26.0
Requires-Dist: torch
Requires-Dist: torchvision==0.15.2
Requires-Dist: torchtext
Requires-Dist: Pillow
Requires-Dist: tqdm
Requires-Dist: fsspec
Requires-Dist: gcsfs
Requires-Dist: matplotlib
